Metadata-Version: 2.1
Name: stackvar
Version: 3.1.0
Summary: Dispatch function's parameters through the callstack omitting arguments on intermediary functions. (a.k.a.: stack variable)
Home-page: https://gitlab.com/joaduo/stackvar
Author: Joaquin Duo
Author-email: joaduo@gmail.com
License: MIT
Keywords: stack,callstack,variable,parameter
Platform: UNKNOWN
License-File: LICENSE
